{
  "id": "1bb94e2c-0b09-490e-a03d-a54a521f65c5",
  "name": "Quick Sequential Layout",
  "description": "Automatically created sequential layout",
  "width": 1920,
  "height": 1080,
  "fps": 30,
  "tracks": [
    {
      "name": "Track 1",
      "items": [
        {
          "id": "531adda6-72f4-4d50-8bc0-ef26464d6d2f",
          "type": "video",
          "src": "/uploads/1755414724362-shot_01.mp4",
          "from": 0,
          "durationInFrames": 146
        },
        {
          "id": "996c6fe8-5e4c-4a28-b07f-b784dd47e056",
          "type": "video",
          "src": "/uploads/1755414724421-shot_02.mp4",
          "from": 146,
          "durationInFrames": 146
        },
        {
          "id": "ab354ae9-7084-4218-9652-74f73ffff893",
          "type": "video",
          "src": "/uploads/1755414724479-shot_03.mp4",
          "from": 292,
          "durationInFrames": 146
        },
        {
          "id": "b9ce6df1-0d5e-408a-af13-1ef040d1c6f6",
          "type": "video",
          "src": "/uploads/1755414724535-shot_04.mp4",
          "from": 438,
          "durationInFrames": 146
        },
        {
          "id": "6d944209-0af6-445f-b66f-ca949c98a097",
          "type": "video",
          "src": "/uploads/1755414724591-shot_05.mp4",
          "from": 585,
          "durationInFrames": 146
        },
        {
          "id": "b841b5c8-9bb5-4a1f-a385-5264a253d895",
          "type": "video",
          "src": "/uploads/1755414724647-shot_06.mp4",
          "from": 731,
          "durationInFrames": 146
        },
        {
          "id": "01faf414-7b72-458c-bce1-df06a864f1c9",
          "type": "video",
          "src": "/uploads/1755414724705-shot_07.mp4",
          "from": 877,
          "durationInFrames": 877
        }
      ]
    }
  ],
  "createdAt": "2025-08-17T12:57:34.623Z",
  "updatedAt": "2025-08-18T05:24:16.999Z",
  "media": []
}